Workbook
Name Slicer_Category: #N/A
Name Slicer_City: #N/A

Sheet Data
A1: Order ID | B1: Order Date | C1: Customer ID | D1: Customer Name | E1: City | F1: State | G1: Product ID | H1: Product Name | I1: Category | J1: Quantity | K1: Unit Price | L1: Sales Amount | M1: Profit | N1: Payment Mode | O1: Order Status | P1: Sales Category
A2: ORD00001 | B2: 45942 | C2: C0170 | D2: Aarav Shah | E2: Indore | F2: Madhya Pradesh | G2: P1005 | H2: Smart Watch | I2: Electronics | J2: 4 | K2: 3999 | L2: 15996 | M2: 5328.52 | N2: Net Banking | O2: Completed | P2: =IF(L2>=10000,"High Value",IF(L2>=5000,"Medium Value","Low Value")) -> High Value
A3: ORD00002 | B3: 45818 | C3: C0015 | D3: Rohan Verma | E3: Ahmedabad | F3: Gujarat | G3: P1019 | H3: Hair Dryer | I3: Beauty | J3: 8 | K3: 1679 | L3: 11417.2 | M3: 1765.5 | N3: Net Banking | O3: Completed | P3: =IF(L3>=10000,"High Value",IF(L3>=5000,"Medium Value","Low Value")) -> High Value
A4: ORD00003 | B4: 45693 | C4: C0153 | D4: Kiara Nair | E4: Vadodara | F4: Gujarat | G4: P1008 | H4: Backpack | I4: Fashion | J4: 7 | K4: 1169 | L4: 6955.55 | M4: 1211.43 | N4: Net Banking | O4: Completed | P4: =IF(L4>=10000,"High Value",IF(L4>=5000,"Medium Value","Low Value")) -> Medium Value
A5: ORD00004 | B5: 45872 | C5: C0169 | D5: Dev Prajapati | E5: Bhopal | F5: Madhya Pradesh | G5: P1011 | H5: Desk Lamp | I5: Home & Kitchen | J5: 5 | K5: 899 | L5: 3596 | M5: 998.11 | N5: Credit Card | O5: Completed | P5: =IF(L5>=10000,"High Value",IF(L5>=5000,"Medium Value","Low Value")) -> Low Value
A6: ORD00005 | B6: 46001 | C6: C0166 | D6: Aditya Iyer | E6: Delhi | F6: Delhi | G6: P1015 | H6: Study Desk | I6: Furniture | J6: 6 | K6: 7199 | L6: 43194 | M6: 9538.22 | N6: Net Banking | O6: Returned | P6: =IF(L6>=10000,"High Value",IF(L6>=5000,"Medium Value","Low Value")) -> High Value
A7: ORD00006 | B7: 45933 | C7: C0055 | D7: Dhruv Sharma | E7: Bhopal | F7: Madhya Pradesh | G7: P1009 | H7: Water Bottle | I7: Home & Kitchen | J7: 3 | K7: 399 | L7: 1197 | M7: 375.19 | N7: Debit Card | O7: Completed | P7: =IF(L7>=10000,"High Value",IF(L7>=5000,"Medium Value","Low Value")) -> Low Value
A8: ORD00007 | B8: 45936 | C8: C0078 | D8: Vivaan Prajapati | E8: Bhopal | F8: Madhya Pradesh | G8: P1001 | H8: Wireless Mouse | I8: Electronics | J8: 5 | K8: 659 | L8: 3295 | M8: 1076.03 | N8: Credit Card | O8: Completed | P8: =IF(L8>=10000,"High Value",IF(L8>=5000,"Medium Value","Low Value")) -> Low Value
A9: ORD00008 | B9: 45941 | C9: C0040 | D9: Ishaan Prajapati | E9: Udaipur | F9: Rajasthan | G9: P1010 | H9: Coffee Maker | I9: Home & Kitchen | J9: 4 | K9: 3629 | L9: 13790.2 | M9: 2272.51 | N9: Debit Card | O9: Completed | P9: =IF(L9>=10000,"High Value",IF(L9>=5000,"Medium Value","Low Value")) -> High Value
A10: ORD00009 | B10: 45684 | C10: C0024 | D10: Aadhya Shah | E10: Chennai | F10: Tamil Nadu | G10: P1009 | H10: Water Bottle | I10: Home & Kitchen | J10: 1 | K10: 359 | L10: 341.05 | M10: 98.78 | N10: Debit Card | O10: Completed | P10: =IF(L10>=10000,"High Value",IF(L10>=5000,"Medium Value","Low Value")) -> Low Value
A11: ORD00010 | B11: 45940 | C11: C0110 | D11: Kiara Trivedi | E11: Lucknow | F11: Uttar Pradesh | G11: P1001 | H11: Wireless Mouse | I11: Electronics | J11: 2 | K11: 539 | L11: 862.4 | M11: 274.99 | N11: Net Banking | O11: Completed | P11: =IF(L11>=10000,"High Value",IF(L11>=5000,"Medium Value","Low Value")) -> Low Value
A12: ORD00011 | B12: 45956 | C12: C0142 | D12: Krishna Desai | E12: Mumbai | F12: Maharashtra | G12: P1014 | H12: Office Chair | I12: Furniture | J12: 3 | K12: 5849 | L12: 16669.65 | M12: 3337.65 | N12: UPI | O12: Cancelled | P12: =IF(L12>=10000,"High Value",IF(L12>=5000,"Medium Value","Low Value")) -> High Value
A13: ORD00012 | B13: 46007 | C13: C0064 | D13: Rohan Reddy | E13: Rajkot | F13: Gujarat | G13: P1012 | H13: Notebook Set | I13: Stationery | J13: 7 | K13: 261 | L13: 1461.6 | M13: 225.09 | N13: Credit Card | O13: Cancelled | P13: =IF(L13>=10000,"High Value",IF(L13>=5000,"Medium Value","Low Value")) -> Low Value
... A800: ORD00799 | B800: 45756 | C800: C0114 | D800: Aditya Sharma | E800: Surat | F800: Gujarat | G800: P1008 | H800: Backpack | I800: Fashion | J800: 1 | K800: 1299 | L800: 1039.2 | M800: 335.36 | N800: Debit Card | O800: Completed | P800: =IF(L800>=10000,"High Value",IF(L800>=5000,"Medium Value","Low Value")) -> Low Value

Sheet Analysis
A1: Product Vlookup | D1: Index Match | H1: Total Visits | K1: Total Sale
A2: Input (Product ID) | B2: P1001 | D2: Input (Customer ID) | E2: C0174 | H2: =COUNTA(data[Order ID]) -> 799 | K2: =SUM(data[Sales Amount]) -> 6736567.6
A3: Output (Product Name) | B3: =IFERROR(VLOOKUP(B2, data[[Product ID]:[Product Name]], 2, FALSE), "Not Found") -> Wireless Mouse | D3: Output (Customer Name) | E3: =IFERROR(INDEX(data[Customer Name], MATCH(Analysis!E2, data[Customer ID],0)), "Not Found") -> Myra Trivedi
H4: Average Sale | K4: Total Quantity Sold
H5: =AVERAGE(data[Sales Amount]) -> 8431.2486 | K5: =SUM(Data!J775:J800) -> 96
A6: SUMIF (Total Sales by Product) | D6: COUNTIF (No. of Order by State)
A7: Office Chair | B7: =SUMIF(data[Product Name], A7, data[Sales Amount]) -> 1072432.6 | D7: Delhi | E7: =COUNTIF(data[State],D7) -> 51 | H7: Profit Margin (%) | K7: Completed Orders
H8: =IFERROR(SUM(data[Profit])/SUM(data[Sales Amount]),0) -> 0.23122413 | K8: =COUNTIF(data[Order Status],"Completed") -> 588
H10: Total Profit
A11: Highest sale | D11: Lowest sale | H11: =SUM(data[Profit]) -> 1557657
A12: Product Name | B12: =_xlfn.XLOOKUP(B14, data[Sales Amount], data[Product Name]) -> Study Desk | D12: Product Name | E12: =_xlfn.XLOOKUP(E14, data[Sales Amount], data[Product Name]) -> Gel Pen Pack
A13: Category | B13: =_xlfn.XLOOKUP(B14, data[Sales Amount], data[Category]) -> Furniture | D13: Category | E13: =_xlfn.XLOOKUP(E14, data[Sales Amount], data[Category]) -> Stationery
A14: Total Amount | B14: =MAX(Data!L776:L800) -> 25077.15 | D14: Total Amount | E14: =MIN(data[Sales Amount]) -> 107.2

Sheet Pivot Table
A1: Month | B1: Total Sales | D1: Product Category | E1: No. of Order | G1: State | H1: Total Sales | K1: Top 10 Product | L1: Total Sales
A2: Jan | B2: 568603.4 | D2: Stationery | E2: 72 | G2: Kerala | H2: 273730.85 | K2: Study Desk | L2: 1744262.6
A3: Feb | B3: 409730.9 | D3: Sports | E3: 85 | G3: Tamil Nadu | H3: 404079.4 | K3: Office Chair | L3: 1072432.6
A4: Mar | B4: 683203.55 | D4: Furniture | E4: 91 | G4: Delhi | H4: 408158.6 | K4: Coffee Maker | L4: 514112
A5: Apr | B5: 479137 | D5: Beauty | E5: 92 | G5: Uttar Pradesh | H5: 421864 | K5: Smart Watch | L5: 476559.8
A6: May | B6: 484355.65 | D6: Fashion | E6: 118 | G6: Telangana | H6: 449421.6 | K6: Mechanical Keyboard | L6: 346363.95
A7: Jun | B7: 471561.15 | D7: Home & Kitchen | E7: 159 | G7: Madhya Pradesh | H7: 741113.8 | K7: Bluetooth Speaker | L7: 314794.7
A8: Jul | B8: 660978.45 | D8: Electronics | E8: 182 | G8: Rajasthan | H8: 754445.85 | K8: Hair Dryer | L8: 309601.3
A9: Aug | B9: 409893.2 | D9: Grand Total | E9: 799 | G9: Karnataka | H9: 893502.7 | K9: Cricket Bat | L9: 309237.65
A10: Sep | B10: 623376.6 | G10: Gujarat | H10: 1136672.3 | K10: Running Shoes | L10: 268230.2
A11: Oct | B11: 567291.7 | G11: Maharashtra | H11: 1253578.5 | K11: USB-C Hub | L11: 261401.8
A12: Nov | B12: 621739.3 | D12: Payment Mode | E12: No. Of Order | G12: Grand Total | H12: 6736567.6 | K12: Grand Total | L12: 5616996.5
A13: Dec | B13: 756696.7 | D13: Cash | E13: 170
A14: Grand Total | B14: 6736567.6 | D14: Credit Card | E14: 166 | G14: Status | H14: No. Of Order
D15: Debit Card | E15: 158 | G15: Completed | H15: 588
D16: Net Banking | E16: 162 | G16: Pending | H16: 81
A17: Top 10 Customers | B17: Total Sales | D17: UPI | E17: 143 | G17: Cancelled | H17: 80
A18: Dhruv Prajapati | B18: 160108.55 | D18: Grand Total | E18: 799 | G18: Returned | H18: 50
A19: Nisha Kumar | B19: 159836.4 | G19: Grand Total | H19: 799
A20: Krishna Joshi | B20: 137793.75
A21: Nisha Nair | B21: 133201.15
A22: Aarav Shah | B22: 131625.25
A23: Ishaan Patel | B23: 119888.45
A24: Ishaan Mehta | B24: 116768.8
A25: Aditya Rao | B25: 116516.2
A26: Reyansh Sharma | B26: 114636.55
A27: Dev Rao | B27: 111053.4
A28: Grand Total | B28: 1301428.5

Sheet Dashboard
B2: E-COMMERCE SALES DASHBOARD
B3: JAN–DEC 2025 | REVENUE • PROFITABILITY • ORDERS | INTERACTIVE ANALYTICS
B7: TOTAL SALES | E7: TOTAL PROFIT | H7: PROFIT MARGIN | K7: TOTAL ORDERS | N7: AVG ORDER VALUE | Q7: Completed Orders
B8: =Analysis!K2/100000 -> 67.365676 | E8: =Analysis!H11/100000 -> 15.57657 | H8: =IFERROR(Analysis!H8,0) -> 0.23122413 | K8: =Analysis!H2 -> 799 | N8: =IFERROR(Analysis!H5,0) -> 8431.2486 | Q8: =IFERROR(Analysis!K8,0) -> 588
B11: FILTERS
B104: KEY INSIGHTS
B106: TOP MARKETS | H106: SEASONALITY | N106: STAR PRODUCT
B107: Maharashtra leads with ₹12.5 L in sales, contributing 19% of total revenue. | H107: Monthly sales trends reveal changes in revenue throughout the year. | N107: Study Desk leads with ₹25,077 in sales, making it the top product by revenue.
B110: PROFITABILITY | H110: ORDER HEALTH | N110: ORDER MIX
B111: Office Chair generates ₹10.72 L in sales. Compare its profit contribution and margin to evaluate profitability. | H111: Monitor completed, pending, cancelled, and returned orders to identify order-processing issues. | N111: UPI and Net Banking are the most popular payment methods.
